basecmd/__init__.py
basecmd/__main__.py
basecmd-0.1.6.dist-info/licenses/LICENSE.txt
basecmd-0.1.6.dist-info/METADATA
basecmd-0.1.6.dist-info/WHEEL
basecmd-0.1.6.dist-info/top_level.txt
basecmd-0.1.6.dist-info/RECORD
