Metadata-Version: 2.4
Name: basecmd
Version: 0.1.6
Summary: Logging boilerplate for the command line
Author: dnknth
License-Expression: MIT
Project-URL: Repository, https://github.com/dnknth/basecmd
Classifier: Operating System :: OS Independent
Classifier: Development Status :: 3 - Alpha
Classifier: Intended Audience :: Developers
Classifier: Topic :: Software Development :: Libraries
Requires-Python: >=3.7
License-File: LICENSE.txt
Requires-Dist: ansicolors
Requires-Dist: python-decouple
Dynamic: license-file
